<sectors sequence="0,1,0">
	<sector id="0" name="R Receiver" width="1288" height="335" reference="2" polygon="m 0 0 l 0 245 l 274 0 l 0 -91 l 573 0 l 0 181 l 198 0 l 0 -181 l 243 0 l 0 -119 l -16 0 l 0 -35 l -200 0 l 0 35 l -798 0 l 0 -35 z">
		<landmarks>
			<!--Laser landmarks-->
			<landmark id="0" type="laser" x="890" y="35" z="0"/>
			<landmark id="1" type="laser" x="595" y="154" z="0"/>
			<landmark id="2" type="laser" x="343" y="35" z="0"/>
			<landmark id="3" type="laser" x="19" y="0" z="0"/>
			<landmark id="4" type="laser" x="235" y="0" z="0"/>
			<landmark id="5" type="laser" x="0" y="150" z="0"/>
			<landmark id="6" type="laser" x="275" y="165" z="0"/>
			<!--Camera landmarks-->
			<landmark id="4" type="camera" x="0" y="150" z="250"/>
			<landmark id="0" type="camera" x="195" y="300" z="240"/>
			<landmark id="1" type="camera" x="358" y="468" z="248"/>
			<landmark id="2" type="camera" x="610" y="300" z="245"/>
			<landmark id="3" type="camera" x="905" y="468" z="247"/>
		</landmarks>
		<features>
			<feature id="2" name="charger" width="50" height="25" x="658" y="397" linked-sector-id="7" xcoord="420" ycoord="0"/>
		</features>
		<sites cyclic="no" sequence="12,0,1,2,8">
			<site id="0" name="doorway" radius="0" tsec="0" x="900" y="300" linked-feature-id="1"/>
		</sites>
	</sector>
	<sector id="1" name="Main Hall" width="2865" height="521" reference="2" polygon="m 0 277 l 0 168 l 127 0 l 0 53 l 101 0 l 0 -53 l 2383 0 l 0 53 l 115 0 l 0 -53 l 91 0 l 0 -468 l -254 0 l 0 300 z">
		<landmarks>
			<!--Laser landmarks-->
			<landmark id="0" type="laser" x="118" y="300" z="0"/>
			<landmark id="1" type="laser" x="118" y="468" z="0"/>
			<landmark id="2" type="laser" x="472" y="300" z="0"/>
			<landmark id="3" type="laser" x="472" y="468" z="0"/>
			<landmark id="4" type="laser" x="904" y="300" z="0"/>
			<landmark id="5" type="laser" x="904" y="468" z="0"/>
			<landmark id="6" type="laser" x="1608" y="300" z="0"/>
			<landmark id="7" type="laser" x="1608" y="468" z="0"/>
			<landmark id="8" type="laser" x="2024" y="468" z="0"/>
			<landmark id="9" type="laser" x="2395" y="300" z="0"/>
			<landmark id="10" type="laser" x="2395" y="468" z="0"/>
			<landmark id="11" type="laser" x="2600" y="468" z="0"/>
			<landmark id="12" type="laser" x="2865" y="209" z="0"/>
			<landmark id="13" type="laser" x="2610" y="209" z="0"/>
			<landmark id="14" type="laser" x="2646" y="0" z="0"/>
			<!--Camera landmarks-->
			<landmark id="0" type="camera" x="0" y="338" z="243"/>
			<landmark id="8" type="camera" x="487" y="300" z="249"/>
			<landmark id="10" type="camera" x="636" y="468" z="256"/>
			<landmark id="2" type="camera" x="926" y="300" z="244"/>
			<landmark id="1" type="camera" x="1429" y="468" z="255"/>
			<landmark id="3" type="camera" x="1623" y="300" z="247"/>
			<landmark id="9" type="camera" x="2039" y="468" z="257"/>
			<landmark id="5" type="camera" x="2410" y="300" z="247"/>
			<landmark id="4" type="camera" x="2616" y="468" z="248"/>
			<landmark id="7" type="camera" x="2865" y="224" z="247"/>
			<landmark id="6" type="camera" x="2683" y="0" z="243"/>
		</landmarks>
		<features>
			<feature id="2" name="charger" width="50" height="25" x="658" y="397" linked-sector-id="7" xcoord="420" ycoord="0"/>
		</features>
		<sites cyclic="no" sequence="12,0,1,2,8">
			<site id="0" name="doorway" radius="0" tsec="0" x="900" y="300" linked-feature-id="1"/>
		</sites>
	</sector>
	<sector id="2" name="LCOE Receiver" width="897" height="432" reference="2" polygon="m 0 0 l 0 432 l 897 0 l 0 -432 z">
		<landmarks>
			
		</landmarks>
		<features>
			<feature id="2" name="charger" width="50" height="25" x="658" y="397" linked-sector-id="7" xcoord="420" ycoord="0"/>
		</features>
		<sites cyclic="no" sequence="12,0,1,2,8">
			<site id="0" name="doorway" radius="0" tsec="0" x="900" y="300" linked-feature-id="1"/>
		</sites>
	</sector>
	<sector id="3" name="R4" width="573" height="557" reference="2" polygon="m 0 0 l 0 557 l 573 0 l 0 -557 z">
		<landmarks>
			
		</landmarks>
		<features>
			<feature id="2" name="charger" width="50" height="25" x="658" y="397" linked-sector-id="7" xcoord="420" ycoord="0"/>
		</features>
		<sites cyclic="no" sequence="12,0,1,2,8">
			<site id="0" name="doorway" radius="0" tsec="0" x="900" y="300" linked-feature-id="1"/>
		</sites>
	</sector>
	<sector id="4" name="R3" width="549" height="509" reference="2" polygon="m 0 0 l 0 509 l 549 0 l 0 -509 z">
		<landmarks>
			
		</landmarks>
		<features>
			<feature id="2" name="charger" width="50" height="25" x="658" y="397" linked-sector-id="7" xcoord="420" ycoord="0"/>
		</features>
		<sites cyclic="no" sequence="12,0,1,2,8">
			<site id="0" name="doorway" radius="0" tsec="0" x="900" y="300" linked-feature-id="1"/>
		</sites>
	</sector>
	<sector id="5" name="R2" width="1017" height="509" reference="2" polygon="m 0 0 l 0 509 l 1017 0 l 0 -509 z">
		<landmarks>
			
		</landmarks>
		<features>
			<feature id="2" name="charger" width="50" height="25" x="658" y="397" linked-sector-id="7" xcoord="420" ycoord="0"/>
		</features>
		<sites cyclic="no" sequence="12,0,1,2,8">
			<site id="0" name="doorway" radius="0" tsec="0" x="900" y="300" linked-feature-id="1"/>
		</sites>
	</sector>
	<sector id="6" name="R1" width="750" height="509" reference="2" polygon="m 0 0 l 0 509 l 750 0 l 0 -509 z">
		<landmarks>
			
		</landmarks>
		<features>
			<feature id="2" name="charger" width="50" height="25" x="658" y="397" linked-sector-id="7" xcoord="420" ycoord="0"/>
		</features>
		<sites cyclic="no" sequence="12,0,1,2,8">
			<site id="0" name="doorway" radius="0" tsec="0" x="900" y="300" linked-feature-id="1"/>
		</sites>
	</sector>
	
</sectors>